CGRtools/__init__.py
CGRtools/_functions.py
CGRtools/exceptions.py
CGRtools/preparer.py
CGRtools/algorithms/__init__.py
CGRtools/algorithms/aromatics.py
CGRtools/algorithms/depict.py
CGRtools/algorithms/huckel.py
CGRtools/algorithms/isomorphism.py
CGRtools/algorithms/mcs.py
CGRtools/algorithms/morgan.py
CGRtools/algorithms/smiles.py
CGRtools/algorithms/sssr.py
CGRtools/algorithms/stereo.py
CGRtools/algorithms/tautomers.py
CGRtools/algorithms/x3dom.py
CGRtools/algorithms/calculate2d/__init__.py
CGRtools/algorithms/calculate2d/clean2d.js
CGRtools/algorithms/components/__init__.py
CGRtools/algorithms/components/cgr.py
CGRtools/algorithms/components/graph.py
CGRtools/algorithms/components/reaction.py
CGRtools/algorithms/components/structure.py
CGRtools/algorithms/standardize/__init__.py
CGRtools/algorithms/standardize/molecule.py
CGRtools/algorithms/standardize/reaction.py
CGRtools/attributes/__init__.py
CGRtools/attributes/molecule.py
CGRtools/attributes/query.py
CGRtools/containers/__init__.py
CGRtools/containers/_unpack.cp38-win_amd64.pyd
CGRtools/containers/_unpack.pyx
CGRtools/containers/bonds.py
CGRtools/containers/cgr.py
CGRtools/containers/cgr_query.py
CGRtools/containers/common.py
CGRtools/containers/molecule.py
CGRtools/containers/query.py
CGRtools/containers/reaction.py
CGRtools/files/INCHIrw.py
CGRtools/files/MRVrw.py
CGRtools/files/PDBrw.py
CGRtools/files/RDFrw.py
CGRtools/files/SDFrw.py
CGRtools/files/SMILESrw.py
CGRtools/files/XYZrw.py
CGRtools/files/__init__.py
CGRtools/files/_mdl/__init__.py
CGRtools/files/_mdl/emol.py
CGRtools/files/_mdl/erxn.py
CGRtools/files/_mdl/ewrite.py
CGRtools/files/_mdl/mol.py
CGRtools/files/_mdl/parser.py
CGRtools/files/_mdl/rw.py
CGRtools/files/_mdl/rxn.py
CGRtools/files/_mdl/stereo.py
CGRtools/files/_mdl/write.py
CGRtools/periodictable/__init__.py
CGRtools/periodictable/groupI.py
CGRtools/periodictable/groupII.py
CGRtools/periodictable/groupIII.py
CGRtools/periodictable/groupIV.py
CGRtools/periodictable/groupIX.py
CGRtools-4.1.35.dist-info/LICENSE
CGRtools-4.1.35.dist-info/METADATA
CGRtools-4.1.35.dist-info/WHEEL
CGRtools-4.1.35.dist-info/top_level.txt
CGRtools-4.1.35.dist-info/RECORD
