Metadata-Version: 2.1
Name: CGRtools
Version: 4.1.35
Home-page: https://github.com/cimm-kzn/CGRtools
Author: Dr. Ramil Nugmanov, Dr. Timur Madzhidov, Valentina Afonina
Author-email: tmadzhidov@gmail.com
License: LGPLv3
Classifier: Environment :: Plugins
Classifier: Intended Audience :: Science/Research
Classifier: License :: OSI Approved :: GNU Lesser General Public License v3 or later (LGPLv3+)
Classifier: Operating System :: OS Independent
Classifier: Programming Language :: Python
Classifier: Programming Language :: Python :: 3 :: Only
Classifier: Programming Language :: Python :: 3.7
Classifier: Programming Language :: Python :: 3.8
Classifier: Programming Language :: Python :: 3.9
Classifier: Programming Language :: Python :: 3.10
Classifier: Topic :: Scientific/Engineering
Classifier: Topic :: Scientific/Engineering :: Chemistry
Classifier: Topic :: Scientific/Engineering :: Information Analysis
Classifier: Topic :: Software Development
Classifier: Topic :: Software Development :: Libraries
Classifier: Topic :: Software Development :: Libraries :: Python Modules
Requires-Python: >=3.6.1
License-File: LICENSE
Requires-Dist: CachedMethods (<0.2,>=0.1.4)
Provides-Extra: clean2d
Requires-Dist: py-mini-racer (>=0.4.0) ; extra == 'clean2d'
Provides-Extra: jit
Requires-Dist: numpy (>=1.18) ; extra == 'jit'
Requires-Dist: numba (>=0.50) ; extra == 'jit'
Provides-Extra: mrv
Requires-Dist: lxml (>=4.1) ; extra == 'mrv'
